facebook_page_scraper/__init__.py
facebook_page_scraper/__version__.py
facebook_page_scraper/page_info.py
facebook_page_scraper/page_post_info.py
facebook_page_scraper/request_handler.py
facebook_pages_scraper-0.0.4.dist-info/licenses/LICENSE
facebook_pages_scraper-0.0.4.dist-info/METADATA
facebook_pages_scraper-0.0.4.dist-info/WHEEL
facebook_pages_scraper-0.0.4.dist-info/top_level.txt
facebook_pages_scraper-0.0.4.dist-info/RECORD
